jalap/__init__.py
jalap-0.0.1.dist-info/METADATA
jalap-0.0.1.dist-info/WHEEL
jalap-0.0.1.dist-info/top_level.txt
jalap-0.0.1.dist-info/RECORD
