Metadata-Version: 2.4
Name: jalap
Version: 0.0.1
Summary: JSON transformation
Requires-Python: >=3.7
